apachedex/__init__.py
apachedex/__main__.py
apachedex/_version.py
apachedex/apachedex.css
apachedex/apachedex.js
apachedex/jquery-ui.js
apachedex/jquery.flot.axislabels.js
apachedex/jquery.flot.js
apachedex/jquery.flot.time.js
apachedex/jquery.js
apachedex/tests.py
apachedex-2.2.dist-info/licenses/COPYING
apachedex-2.2.dist-info/METADATA
apachedex-2.2.dist-info/WHEEL
apachedex-2.2.dist-info/entry_points.txt
apachedex-2.2.dist-info/top_level.txt
apachedex-2.2.dist-info/zip-safe
apachedex-2.2.dist-info/RECORD
