Metadata-Version: 2.4
Name: APacheDEX
Version: 2.2
Summary: Compute APDEX from Apache-style logs.
Home-page: https://lab.nexedi.com/nexedi/apachedex.git
Author: Vincent Pelletier
Author-email: vincent@nexedi.com
License: GPL 2+
Platform: any
Classifier: Intended Audience :: Developers
Classifier: License :: OSI Approved :: GNU General Public License v2 or later (GPLv2+)
Classifier: Operating System :: OS Independent
Classifier: Programming Language :: Python :: 3
Classifier: Programming Language :: Python :: Implementation :: PyPy
Classifier: Programming Language :: Python :: Implementation :: CPython
Classifier: Topic :: System :: Logging
Classifier: Topic :: Text Processing :: Filters
Classifier: Topic :: Text Processing :: Markup :: HTML
License-File: COPYING
Dynamic: author
Dynamic: author-email
Dynamic: classifier
Dynamic: description
Dynamic: description-content-type
Dynamic: home-page
Dynamic: license
Dynamic: license-file
Dynamic: platform
Dynamic: summary
